tlapi/__init__.py
tlapi/api.py
tlapi/debug.py
tlapi/devices.py
tlapi/exception.py
tlapi/utils.py
tlapi/td/__init__.py
tlapi/td/account.py
tlapi/td/auth.py
tlapi/td/configs.py
tlapi/td/mtp.py
tlapi/td/shared.py
tlapi/td/storage.py
tlapi/td/tdesktop.py
tlapi/tl/__init__.py
tlapi/tl/configs.py
tlapi/tl/shared.py
tlapi/tl/telethon.py
tlapi-0.0.2.dist-info/METADATA
tlapi-0.0.2.dist-info/WHEEL
tlapi-0.0.2.dist-info/top_level.txt
tlapi-0.0.2.dist-info/RECORD
