Metadata-Version: 2.1
Name: tlapi
Version: 0.0.2
Summary: A Python Telegram API Library for converting between tdata and telethon sessions, with built-in official Telegram APIs.
Home-page: https://github.com/hashemdalijeh/tlapi
Author: hashemdalijeh
Author-email: hashemdalijeh@gmail.com
License: MIT
Keywords: tdata,tdesktop,telegram,telethon,opentele,tlapi,official_Telegram_APIs,tl_api,Telegram_API
Classifier: License :: OSI Approved :: MIT License
Classifier: Operating System :: Microsoft :: Windows
Classifier: Operating System :: MacOS
Classifier: Operating System :: POSIX :: Linux
Classifier: Programming Language :: Python :: 3
Classifier: Programming Language :: Python :: 3.10
Requires-Dist: pyqt5
Requires-Dist: telethon
Requires-Dist: tgcrypto
